AUTHORS
LICENSE
MANIFEST.in
README.rst
setup.cfg
setup.py
docs/bestpractice.rst
docs/changelog.rst
docs/conf.py
docs/contributing.rst
docs/customization.rst
docs/dashboard_api.rst
docs/dashboard_setup.rst
docs/djangoissues.rst
docs/faq.rst
docs/help.rst
docs/index.rst
docs/internals.rst
docs/javascripts.rst
docs/quickstart.rst
docs/releasenotes.rst
docs/templates.rst
docs/thirdparty.rst
docs/troubleshooting.rst
grappelli/__init__.py
grappelli/apps.py
grappelli/checks.py
grappelli/forms.py
grappelli/models.py
grappelli/settings.py
grappelli/urls.py
grappelli/urls_docs.py
grappelli/dashboard/__init__.py
grappelli/dashboard/apps.py
grappelli/dashboard/dashboards.py
grappelli/dashboard/modules.py
grappelli/dashboard/registry.py
grappelli/dashboard/utils.py
grappelli/dashboard/management/__init__.py
grappelli/dashboard/management/commands/__init__.py
grappelli/dashboard/management/commands/customdashboard.py
grappelli/dashboard/templates/admin/index.html
grappelli/dashboard/templates/grappelli/dashboard/dashboard.html
grappelli/dashboard/templates/grappelli/dashboard/dashboard.txt
grappelli/dashboard/templates/grappelli/dashboard/dummy.html
grappelli/dashboard/templates/grappelli/dashboard/module.html
grappelli/dashboard/templates/grappelli/dashboard/modules/app_list.html
grappelli/dashboard/templates/grappelli/dashboard/modules/feed.html
grappelli/dashboard/templates/grappelli/dashboard/modules/group.html
grappelli/dashboard/templates/grappelli/dashboard/modules/link_list.html
grappelli/dashboard/templates/grappelli/dashboard/modules/model_list.html
grappelli/dashboard/templates/grappelli/dashboard/modules/recent_actions.html
grappelli/dashboard/templatetags/__init__.py
grappelli/dashboard/templatetags/grp_dashboard_tags.py
grappelli/static/admin/js/actions.js
grappelli/static/admin/js/admin/DateTimeShortcuts.js
grappelli/static/admin/js/admin/RelatedObjectLookups.js
grappelli/static/grappelli/images/icons-s79f97b581c.png
specsa_django_grappelli.egg-info/PKG-INFO
specsa_django_grappelli.egg-info/SOURCES.txt
specsa_django_grappelli.egg-info/dependency_links.txt
specsa_django_grappelli.egg-info/not-zip-safe
specsa_django_grappelli.egg-info/top_level.txt