Metadata-Version: 1.1
Name: specsa-django-grappelli
Version: 0.2
Summary: A jazzy skin for the Django Admin-Interface based on django-grappelli
Home-page: http://django-grappelli.readthedocs.org
Author: Patrick Kranzlmueller, Axel Swoboda (vonautomatisch)
Author-email: office@vonautomatisch.at
License: BSD
Platform: UNKNOWN
Classifier: Development Status :: 5 - Production/Stable
Classifier: Environment :: Web Environment
Classifier: Framework :: Django
Classifier: Intended Audience :: Developers
Classifier: License :: OSI Approved :: BSD License
Classifier: Operating System :: OS Independent
Classifier: Programming Language :: Python :: 3
Classifier: Programming Language :: Python :: 3.6
Classifier: Programming Language :: Python :: 3.7
Classifier: Programming Language :: Python :: 3.8
Classifier: Programming Language :: Python :: 3.9
